mag_com/__init__.py
mag_com/bean/__init__.py
mag_com/bean/password.py
mag_com/com/__init__.py
mag_com/com/http_com.py
mag_com/com/mag_com.py
mag_com/com/safe_com.py
tests/__init__.py
tests/com/__init__.py
tests/com/test_http_com.py
tests/com/test_mag_com.py
tests/com/test_safe_com.py
mag_com-0.0.37.dist-info/METADATA
mag_com-0.0.37.dist-info/WHEEL
mag_com-0.0.37.dist-info/top_level.txt
mag_com-0.0.37.dist-info/RECORD
